waybackscraper/__init__.py
waybackscraper/__main__.py
waybackscraper/cli.py
waybackscraper/exceptions.py
waybackscraper/scraper.py
waybackscraper/wayback.py
waybackscraper/test/__init__.py
waybackscraper/test/wayback_test.py
waybackscraper-0.5.dist-info/DESCRIPTION.rst
waybackscraper-0.5.dist-info/METADATA
waybackscraper-0.5.dist-info/RECORD
waybackscraper-0.5.dist-info/WHEEL
waybackscraper-0.5.dist-info/entry_points.txt
waybackscraper-0.5.dist-info/metadata.json
waybackscraper-0.5.dist-info/top_level.txt
