Metadata-Version: 2.0
Name: waybackscraper
Version: 0.5
Summary: Scrapes a website archives on the wayback machine using asyncio.
Home-page: UNKNOWN
Author: Arthur Brenaut
Author-email: arthur.brenaut@gmail.com
License: UNKNOWN
Platform: UNKNOWN
Requires-Dist: aiohttp
Requires-Dist: lxml
